[{"album": "Blinding Lights", "duration_ms": 201573, "explicit": false, "name": "Blinding Lights", "popularity": 17, "acousticness": 0.00147, "danceability": 0.513, "energy": 0.796, "instrumentalness": 0.000209, "key": 1, "liveness": 0.0938, "loudness": -4.075, "mode": 1, "speechiness": 0.0629, "tempo": 171.017, "time_signature": 4, "valence": 0.345, "artist": "The Weeknd"}, {"album": "Fine Line", "duration_ms": 174000, "explicit": false, "name": "Watermelon Sugar", "popularity": 90, "acousticness": 0.122, "danceability": 0.548, "energy": 0.816, "instrumentalness": 0, "key": 0, "liveness": 0.335, "loudness": -4.209, "mode": 1, "speechiness": 0.0465, "tempo": 95.39, "time_signature": 4, "valence": 0.557, "artist": "Harry Styles"}, {"album": "Please Excuse Me for Being Antisocial", "duration_ms": 196652, "explicit": true, "name": "The Box", "popularity": 80, "acousticness": 0.104, "danceability": 0.896, "energy": 0.586, "instrumentalness": 0, "key": 10, "liveness": 0.79, "loudness": -6.687, "mode": 0, "speechiness": 0.0559, "tempo": 116.971, "time_signature": 4, "valence": 0.642, "artist": "Roddy Ricch"}, {"album": "positions", "duration_ms": 172324, "explicit": true, "name": "positions", "popularity": 6, "acousticness": 0.468, "danceability": 0.736, "energy": 0.802, "instrumentalness": 0, "key": 0, "liveness": 0.094, "loudness": -4.759, "mode": 1, "speechiness": 0.0864, "tempo": 144.005, "time_signature": 4, "valence": 0.675, "artist": "Ariana Grande"}, {"album": "Break My Heart", "duration_ms": 221820, "explicit": false, "name": "Break My Heart", "popularity": 67, "acousticness": 0.167, "danceability": 0.73, "energy": 0.729, "instrumentalness": 1.39e-06, "key": 4, "liveness": 0.349, "loudness": -3.434, "mode": 0, "speechiness": 0.0886, "tempo": 113.012, "time_signature": 4, "valence": 0.467, "artist": "Dua Lipa"}, {"album": "Hot Pink", "duration_ms": 237893, "explicit": true, "name": "Say So", "popularity": 80, "acousticness": 0.264, "danceability": 0.787, "energy": 0.673, "instrumentalness": 3.35e-06, "key": 11, "liveness": 0.0904, "loudness": -4.583, "mode": 0, "speechiness": 0.159, "tempo": 110.962, "time_signature": 4, "valence": 0.779, "artist": "Doja Cat"}, {"album": "Rain On Me (with Ariana Grande)", "duration_ms": 182200, "explicit": false, "name": "Rain On Me (with Ariana Grande)", "popularity": 74, "acousticness": 0.021, "danceability": 0.672, "energy": 0.855, "instrumentalness": 0, "key": 9, "liveness": 0.323, "loudness": -3.764, "mode": 1, "speechiness": 0.0397, "tempo": 123.056, "time_signature": 4, "valence": 0.646, "artist": "Lady Gaga"}, {"album": "Changes", "duration_ms": 212866, "explicit": false, "name": "Intentions (feat. Quavo)", "popularity": 75, "acousticness": 0.3, "danceability": 0.806, "energy": 0.546, "instrumentalness": 0, "key": 9, "liveness": 0.102, "loudness": -6.637, "mode": 1, "speechiness": 0.0575, "tempo": 147.986, "time_signature": 4, "valence": 0.874, "artist": "Justin Bieber"}, {"album": "BLAME IT ON BABY", "duration_ms": 181733, "explicit": true, "name": "ROCKSTAR (feat. Roddy Ricch)", "popularity": 80, "acousticness": 0.247, "danceability": 0.746, "energy": 0.69, "instrumentalness": 0, "key": 11, "liveness": 0.101, "loudness": -7.956, "mode": 1, "speechiness": 0.164, "tempo": 89.977, "time_signature": 4, "valence": 0.497, "artist": "DaBaby"}, {"album": "Mood (feat. iann dior)", "duration_ms": 140525, "explicit": true, "name": "Mood (feat. iann dior)", "popularity": 38, "acousticness": 0.221, "danceability": 0.7, "energy": 0.722, "instrumentalness": 0, "key": 7, "liveness": 0.272, "loudness": -3.558, "mode": 0, "speechiness": 0.0369, "tempo": 90.989, "time_signature": 4, "valence": 0.756, "artist": "24kGoldn"}, {"album": "Shoot For The Stars Aim For The Moon", "duration_ms": 160000, "explicit": true, "name": "What You Know Bout Love", "popularity": 81, "acousticness": 0.65, "danceability": 0.709, "energy": 0.548, "instrumentalness": 1.59e-06, "key": 10, "liveness": 0.133, "loudness": -8.493, "mode": 1, "speechiness": 0.353, "tempo": 83.995, "time_signature": 4, "valence": 0.543, "artist": "Pop Smoke"}, {"album": "WAP (feat. Megan Thee Stallion)", "duration_ms": 187541, "explicit": true, "name": "WAP (feat. Megan Thee Stallion)", "popularity": 80, "acousticness": 0.0194, "danceability": 0.935, "energy": 0.454, "instrumentalness": 0, "key": 1, "liveness": 0.0824, "loudness": -7.509, "mode": 1, "speechiness": 0.375, "tempo": 133.073, "time_signature": 4, "valence": 0.357, "artist": "Cardi B"}, {"album": "death bed (coffee for your head)", "duration_ms": 173333, "explicit": false, "name": "death bed (coffee for your head)", "popularity": 82, "acousticness": 0.731, "danceability": 0.726, "energy": 0.431, "instrumentalness": 0, "key": 8, "liveness": 0.696, "loudness": -8.765, "mode": 0, "speechiness": 0.135, "tempo": 144.026, "time_signature": 4, "valence": 0.348, "artist": "Powfu"}, {"album": "folklore", "duration_ms": 239560, "explicit": false, "name": "cardigan", "popularity": 48, "acousticness": 0.537, "danceability": 0.613, "energy": 0.581, "instrumentalness": 0.000345, "key": 0, "liveness": 0.25, "loudness": -8.588, "mode": 0, "speechiness": 0.0424, "tempo": 130.033, "time_signature": 4, "valence": 0.551, "artist": "Taylor Swift"}, {"album": "Dynamite", "duration_ms": 199053, "explicit": false, "name": "Dynamite", "popularity": 0, "acousticness": 0.0112, "danceability": 0.746, "energy": 0.765, "instrumentalness": 0, "key": 6, "liveness": 0.0936, "loudness": -4.41, "mode": 0, "speechiness": 0.0993, "tempo": 114.044, "time_signature": 4, "valence": 0.737, "artist": "BTS"}, {"album": "Roses (Imanbek Remix)", "duration_ms": 176218, "explicit": true, "name": "Roses - Imanbek Remix", "popularity": 59, "acousticness": 0.0149, "danceability": 0.785, "energy": 0.721, "instrumentalness": 0.00432, "key": 8, "liveness": 0.285, "loudness": -5.457, "mode": 1, "speechiness": 0.0506, "tempo": 121.962, "time_signature": 4, "valence": 0.894, "artist": "SAINt JHN"}, {"album": "Toosie Slide", "duration_ms": 247058, "explicit": true, "name": "Toosie Slide", "popularity": 73, "acousticness": 0.321, "danceability": 0.834, "energy": 0.454, "instrumentalness": 6.15e-06, "key": 1, "liveness": 0.114, "loudness": -9.75, "mode": 0, "speechiness": 0.201, "tempo": 81.618, "time_signature": 4, "valence": 0.837, "artist": "Drake"}, {"album": "B4 The Storm", "duration_ms": 195428, "explicit": true, "name": "Lemonade (feat. Gunna, Don Toliver & NAV)", "popularity": 56, "acousticness": 0.25, "danceability": 0.8, "energy": 0.658, "instrumentalness": 0, "key": 1, "liveness": 0.111, "loudness": -6.142, "mode": 0, "speechiness": 0.079, "tempo": 140.042, "time_signature": 4, "valence": 0.462, "artist": "Internet Money"}, {"album": "Certified Hitmaker", "duration_ms": 162546, "explicit": true, "name": "Blueberry Faygo", "popularity": 75, "acousticness": 0.207, "danceability": 0.774, "energy": 0.554, "instrumentalness": 0, "key": 0, "liveness": 0.132, "loudness": -7.909, "mode": 1, "speechiness": 0.0383, "tempo": 99.034, "time_signature": 4, "valence": 0.349, "artist": "Lil Mosey"}, {"album": "Dance Monkey", "duration_ms": 209754, "explicit": false, "name": "Dance Monkey", "popularity": 62, "acousticness": 0.688, "danceability": 0.826, "energy": 0.593, "instrumentalness": 0.000161, "key": 6, "liveness": 0.17, "loudness": -6.401, "mode": 0, "speechiness": 0.0976, "tempo": 98.083, "time_signature": 4, "valence": 0.541, "artist": "Tones And I"}, {"album": "Don't Start Now", "duration_ms": 183290, "explicit": false, "name": "Don't Start Now", "popularity": 79, "acousticness": 0.0125, "danceability": 0.794, "energy": 0.793, "instrumentalness": 0, "key": 11, "liveness": 0.0952, "loudness": -4.521, "mode": 0, "speechiness": 0.0842, "tempo": 123.941, "time_signature": 4, "valence": 0.677, "artist": "Dua Lipa"}, {"album": "Come & Go (with Marshmello)", "duration_ms": 205484, "explicit": true, "name": "Come & Go (with Marshmello)", "popularity": 63, "acousticness": 0.0173, "danceability": 0.625, "energy": 0.811, "instrumentalness": 0, "key": 0, "liveness": 0.16, "loudness": -5.183, "mode": 1, "speechiness": 0.0659, "tempo": 144.994, "time_signature": 4, "valence": 0.532, "artist": "Juice WRLD"}, {"album": "Stuck with U", "duration_ms": 228482, "explicit": false, "name": "Stuck with U (with Justin Bieber)", "popularity": 82, "acousticness": 0.223, "danceability": 0.597, "energy": 0.45, "instrumentalness": 0, "key": 8, "liveness": 0.382, "loudness": -6.658, "mode": 1, "speechiness": 0.0418, "tempo": 178.765, "time_signature": 3, "valence": 0.537, "artist": "Ariana Grande"}, {"album": "Monster", "duration_ms": 178994, "explicit": false, "name": "Monster (Shawn Mendes & Justin Bieber)", "popularity": 73, "acousticness": 0.0676, "danceability": 0.652, "energy": 0.383, "instrumentalness": 0, "key": 2, "liveness": 0.0828, "loudness": -7.076, "mode": 0, "speechiness": 0.0516, "tempo": 145.765, "time_signature": 4, "valence": 0.549, "artist": "Shawn Mendes"}, {"album": "High Off Life", "duration_ms": 237918, "explicit": true, "name": "Life Is Good (feat. Drake)", "popularity": 71, "acousticness": 0.067, "danceability": 0.795, "energy": 0.574, "instrumentalness": 0, "key": 2, "liveness": 0.15, "loudness": -6.903, "mode": 0, "speechiness": 0.487, "tempo": 142.053, "time_signature": 4, "valence": 0.537, "artist": "Future"}, {"album": "Nicotine", "duration_ms": 159381, "explicit": false, "name": "Falling", "popularity": 3, "acousticness": 0.123, "danceability": 0.784, "energy": 0.43, "instrumentalness": 0, "key": 10, "liveness": 0.0887, "loudness": -8.756, "mode": 0, "speechiness": 0.0364, "tempo": 127.087, "time_signature": 4, "valence": 0.236, "artist": "Trevor Daniel"}, {"album": "D\u00c1KITI", "duration_ms": 205090, "explicit": true, "name": "D\u00c1KITI", "popularity": 81, "acousticness": 0.401, "danceability": 0.731, "energy": 0.573, "instrumentalness": 5.22e-05, "key": 4, "liveness": 0.113, "loudness": -10.059, "mode": 0, "speechiness": 0.0544, "tempo": 109.928, "time_signature": 4, "valence": 0.145, "artist": "Bad Bunny"}, {"album": "Savage Remix (feat. Beyonc\u00e9)", "duration_ms": 242000, "explicit": true, "name": "Savage Remix (feat. Beyonc\u00e9)", "popularity": 68, "acousticness": 0.016, "danceability": 0.822, "energy": 0.743, "instrumentalness": 0, "key": 10, "liveness": 0.127, "loudness": -4.772, "mode": 0, "speechiness": 0.28, "tempo": 84.459, "time_signature": 4, "valence": 0.636, "artist": "Megan Thee Stallion"}, {"album": "you broke me first", "duration_ms": 169265, "explicit": false, "name": "you broke me first", "popularity": 83, "acousticness": 0.785, "danceability": 0.667, "energy": 0.373, "instrumentalness": 0, "key": 4, "liveness": 0.0906, "loudness": -9.389, "mode": 1, "speechiness": 0.05, "tempo": 124.148, "time_signature": 4, "valence": 0.0823, "artist": "Tate McRae"}, {"album": "Hollywood's Bleeding", "duration_ms": 215280, "explicit": false, "name": "Circles", "popularity": 85, "acousticness": 0.192, "danceability": 0.695, "energy": 0.762, "instrumentalness": 0.00244, "key": 0, "liveness": 0.0863, "loudness": -3.497, "mode": 1, "speechiness": 0.0395, "tempo": 120.042, "time_signature": 4, "valence": 0.553, "artist": "Post Malone"}, {"album": "Midnight Sky", "duration_ms": 223279, "explicit": false, "name": "Midnight Sky", "popularity": 49, "acousticness": 0.00115, "danceability": 0.705, "energy": 0.814, "instrumentalness": 0.00312, "key": 4, "liveness": 0.203, "loudness": -5.466, "mode": 0, "speechiness": 0.0346, "tempo": 110.0, "time_signature": 4, "valence": 0.259, "artist": "Miley Cyrus"}, {"album": "Yummy", "duration_ms": 210426, "explicit": false, "name": "Yummy", "popularity": 70, "acousticness": 0.366, "danceability": 0.687, "energy": 0.514, "instrumentalness": 0, "key": 9, "liveness": 0.116, "loudness": -6.612, "mode": 0, "speechiness": 0.0897, "tempo": 145.921, "time_signature": 4, "valence": 0.494, "artist": "Justin Bieber"}, {"album": "Divinely Uninspired To A Hellish Extent (Extended Edition)", "duration_ms": 215106, "explicit": false, "name": "Before You Go", "popularity": 81, "acousticness": 0.604, "danceability": 0.459, "energy": 0.575, "instrumentalness": 0, "key": 3, "liveness": 0.0885, "loudness": -4.858, "mode": 1, "speechiness": 0.0573, "tempo": 111.881, "time_signature": 4, "valence": 0.183, "artist": "Lewis Capaldi"}, {"album": "Manic", "duration_ms": 205473, "explicit": true, "name": "You should be sad", "popularity": 73, "acousticness": 0.143, "danceability": 0.591, "energy": 0.585, "instrumentalness": 0, "key": 2, "liveness": 0.109, "loudness": -6.35, "mode": 1, "speechiness": 0.0277, "tempo": 110.94, "time_signature": 4, "valence": 0.324, "artist": "Halsey"}, {"album": "Fine Line", "duration_ms": 207133, "explicit": false, "name": "Adore You", "popularity": 86, "acousticness": 0.0237, "danceability": 0.676, "energy": 0.771, "instrumentalness": 7e-06, "key": 8, "liveness": 0.102, "loudness": -3.675, "mode": 1, "speechiness": 0.0483, "tempo": 99.048, "time_signature": 4, "valence": 0.569, "artist": "Harry Styles"}, {"album": "How You Like That", "duration_ms": 181263, "explicit": false, "name": "How You Like That", "popularity": 2, "acousticness": 0.0694, "danceability": 0.828, "energy": 0.782, "instrumentalness": 3.41e-05, "key": 11, "liveness": 0.0544, "loudness": -4.014, "mode": 1, "speechiness": 0.0918, "tempo": 130.013, "time_signature": 4, "valence": 0.351, "artist": "BLACKPINK"}, {"album": "Party Girl", "duration_ms": 147800, "explicit": false, "name": "Party Girl", "popularity": 71, "acousticness": 0.749, "danceability": 0.728, "energy": 0.431, "instrumentalness": 0, "key": 6, "liveness": 0.0996, "loudness": -9.966, "mode": 0, "speechiness": 0.0622, "tempo": 130.022, "time_signature": 4, "valence": 0.629, "artist": "StaySolidRocky"}, {"album": "ROXANNE", "duration_ms": 163636, "explicit": true, "name": "ROXANNE", "popularity": 78, "acousticness": 0.0522, "danceability": 0.621, "energy": 0.601, "instrumentalness": 0, "key": 6, "liveness": 0.46, "loudness": -5.616, "mode": 0, "speechiness": 0.148, "tempo": 116.735, "time_signature": 5, "valence": 0.457, "artist": "Arizona Zervas"}, {"album": "Shoot For The Stars Aim For The Moon", "duration_ms": 190476, "explicit": true, "name": "For The Night (feat. Lil Baby & DaBaby)", "popularity": 80, "acousticness": 0.114, "danceability": 0.823, "energy": 0.586, "instrumentalness": 0, "key": 6, "liveness": 0.193, "loudness": -6.606, "mode": 0, "speechiness": 0.2, "tempo": 125.971, "time_signature": 4, "valence": 0.347, "artist": "Pop Smoke"}, {"album": "POPSTAR (feat. Drake)", "duration_ms": 200221, "explicit": true, "name": "POPSTAR (feat. Drake)", "popularity": 74, "acousticness": 0.057, "danceability": 0.8, "energy": 0.56, "instrumentalness": 0, "key": 5, "liveness": 0.134, "loudness": -4.818, "mode": 0, "speechiness": 0.261, "tempo": 163.071, "time_signature": 4, "valence": 0.45, "artist": "DJ Khaled"}, {"album": "Memories", "duration_ms": 189486, "explicit": false, "name": "Memories", "popularity": 32, "acousticness": 0.837, "danceability": 0.764, "energy": 0.32, "instrumentalness": 0, "key": 11, "liveness": 0.0822, "loudness": -7.209, "mode": 1, "speechiness": 0.0546, "tempo": 91.019, "time_signature": 4, "valence": 0.575, "artist": "Maroon 5"}, {"album": "Therefore I Am", "duration_ms": 174321, "explicit": false, "name": "Therefore I Am", "popularity": 75, "acousticness": 0.218, "danceability": 0.889, "energy": 0.34, "instrumentalness": 0.13, "key": 11, "liveness": 0.055, "loudness": -7.773, "mode": 0, "speechiness": 0.0697, "tempo": 94.009, "time_signature": 4, "valence": 0.716, "artist": "Billie Eilish"}, {"album": "Eternal Atake", "duration_ms": 212354, "explicit": true, "name": "That Way - Bonus Track", "popularity": 64, "acousticness": 0.0546, "danceability": 0.712, "energy": 0.598, "instrumentalness": 0, "key": 7, "liveness": 0.154, "loudness": -5.368, "mode": 0, "speechiness": 0.0388, "tempo": 130.007, "time_signature": 4, "valence": 0.504, "artist": "Lil Uzi Vert"}, {"album": "Where the Light Is", "duration_ms": 158571, "explicit": false, "name": "Sunday Best", "popularity": 77, "acousticness": 0.183, "danceability": 0.878, "energy": 0.525, "instrumentalness": 0, "key": 5, "liveness": 0.0714, "loudness": -6.832, "mode": 1, "speechiness": 0.0578, "tempo": 112.022, "time_signature": 4, "valence": 0.694, "artist": "Surfaces"}, {"album": "Positions", "duration_ms": 173710, "explicit": true, "name": "34+35", "popularity": 81, "acousticness": 0.237, "danceability": 0.83, "energy": 0.585, "instrumentalness": 0, "key": 0, "liveness": 0.248, "loudness": -6.476, "mode": 1, "speechiness": 0.094, "tempo": 109.978, "time_signature": 4, "valence": 0.485, "artist": "Ariana Grande"}, {"album": "Prisoner (feat. Dua Lipa)", "duration_ms": 169333, "explicit": false, "name": "Prisoner (feat. Dua Lipa)", "popularity": 51, "acousticness": 0.0103, "danceability": 0.781, "energy": 0.67, "instrumentalness": 0, "key": 3, "liveness": 0.0761, "loudness": -3.912, "mode": 0, "speechiness": 0.0452, "tempo": 127.99, "time_signature": 4, "valence": 0.595, "artist": "Miley Cyrus"}, {"album": "Levitating (feat. DaBaby)", "duration_ms": 203064, "explicit": false, "name": "Levitating (feat. DaBaby)", "popularity": 79, "acousticness": 0.00883, "danceability": 0.702, "energy": 0.825, "instrumentalness": 0, "key": 6, "liveness": 0.0674, "loudness": -3.787, "mode": 0, "speechiness": 0.0601, "tempo": 102.977, "time_signature": 4, "valence": 0.915, "artist": "Dua Lipa"}, {"album": "THE SCOTTS", "duration_ms": 165977, "explicit": true, "name": "THE SCOTTS", "popularity": 75, "acousticness": 0.233, "danceability": 0.716, "energy": 0.537, "instrumentalness": 0, "key": 0, "liveness": 0.157, "loudness": -7.648, "mode": 0, "speechiness": 0.0514, "tempo": 129.979, "time_signature": 4, "valence": 0.28, "artist": "THE SCOTTS"}, {"album": "WHATS POPPIN (feat. DaBaby, Tory Lanez & Lil Wayne) [Remix]", "duration_ms": 227478, "explicit": true, "name": "WHATS POPPIN (feat. DaBaby, Tory Lanez & Lil Wayne) - Remix", "popularity": 76, "acousticness": 0.0631, "danceability": 0.904, "energy": 0.723, "instrumentalness": 0, "key": 11, "liveness": 0.185, "loudness": -5.224, "mode": 0, "speechiness": 0.26, "tempo": 145.013, "time_signature": 4, "valence": 0.835, "artist": "Jack Harlow"}, {"album": "Breaking Me", "duration_ms": 166793, "explicit": false, "name": "Breaking Me", "popularity": 78, "acousticness": 0.223, "danceability": 0.789, "energy": 0.72, "instrumentalness": 0, "key": 8, "liveness": 0.129, "loudness": -5.652, "mode": 0, "speechiness": 0.218, "tempo": 122.031, "time_signature": 4, "valence": 0.664, "artist": "Topic"}, {"album": "Head & Heart (feat. MNEK)", "duration_ms": 166028, "explicit": false, "name": "Head & Heart (feat. MNEK)", "popularity": 81, "acousticness": 0.168, "danceability": 0.734, "energy": 0.874, "instrumentalness": 1.14e-05, "key": 8, "liveness": 0.0489, "loudness": -3.158, "mode": 1, "speechiness": 0.0662, "tempo": 122.953, "time_signature": 4, "valence": 0.905, "artist": "Joel Corry"}, {"album": "Savage Love (Laxed - Siren Beat)", "duration_ms": 171374, "explicit": true, "name": "Savage Love (Laxed - Siren Beat)", "popularity": 77, "acousticness": 0.234, "danceability": 0.767, "energy": 0.481, "instrumentalness": 0, "key": 0, "liveness": 0.269, "loudness": -8.52, "mode": 0, "speechiness": 0.0803, "tempo": 150.076, "time_signature": 4, "valence": 0.761, "artist": "Jawsh 685"}, {"album": "Put Your Records On", "duration_ms": 210463, "explicit": false, "name": "Put Your Records On", "popularity": 77, "acousticness": 0.0563, "danceability": 0.399, "energy": 0.491, "instrumentalness": 0.00089, "key": 6, "liveness": 0.11, "loudness": -10.778, "mode": 0, "speechiness": 0.0538, "tempo": 91.066, "time_signature": 4, "valence": 0.151, "artist": "Ritt Momney"}, {"album": "Laugh Now Cry Later (feat. Lil Durk)", "duration_ms": 261492, "explicit": true, "name": "Laugh Now Cry Later (feat. Lil Durk)", "popularity": 80, "acousticness": 0.244, "danceability": 0.761, "energy": 0.518, "instrumentalness": 3.47e-05, "key": 0, "liveness": 0.107, "loudness": -8.871, "mode": 1, "speechiness": 0.134, "tempo": 133.976, "time_signature": 4, "valence": 0.522, "artist": "Drake"}, {"album": "Music To Be Murdered By", "duration_ms": 210800, "explicit": true, "name": "Godzilla (feat. Juice WRLD)", "popularity": 83, "acousticness": 0.145, "danceability": 0.808, "energy": 0.745, "instrumentalness": 0, "key": 10, "liveness": 0.292, "loudness": -5.26, "mode": 0, "speechiness": 0.342, "tempo": 165.995, "time_signature": 4, "valence": 0.829, "artist": "Eminem"}, {"album": "Holy", "duration_ms": 212093, "explicit": false, "name": "Holy (feat. Chance The Rapper)", "popularity": 75, "acousticness": 0.196, "danceability": 0.673, "energy": 0.704, "instrumentalness": 0, "key": 6, "liveness": 0.0898, "loudness": -8.056, "mode": 1, "speechiness": 0.36, "tempo": 86.919, "time_signature": 4, "valence": 0.372, "artist": "Justin Bieber"}, {"album": "After Hours", "duration_ms": 237520, "explicit": true, "name": "In Your Eyes", "popularity": 78, "acousticness": 0.00285, "danceability": 0.667, "energy": 0.719, "instrumentalness": 8.1e-05, "key": 7, "liveness": 0.0736, "loudness": -5.371, "mode": 0, "speechiness": 0.0346, "tempo": 100.021, "time_signature": 4, "valence": 0.717, "artist": "The Weeknd"}, {"album": "Hey u x", "duration_ms": 223488, "explicit": true, "name": "Supalonely (feat. Gus Dapperton)", "popularity": 63, "acousticness": 0.291, "danceability": 0.862, "energy": 0.631, "instrumentalness": 0.000209, "key": 7, "liveness": 0.123, "loudness": -4.746, "mode": 1, "speechiness": 0.0515, "tempo": 128.978, "time_signature": 4, "valence": 0.841, "artist": "BENEE"}, {"album": "Rare", "duration_ms": 220589, "explicit": false, "name": "Rare", "popularity": 64, "acousticness": 0.208, "danceability": 0.838, "energy": 0.545, "instrumentalness": 8.01e-05, "key": 5, "liveness": 0.103, "loudness": -6.713, "mode": 1, "speechiness": 0.0706, "tempo": 114.998, "time_signature": 4, "valence": 0.631, "artist": "Selena Gomez"}, {"album": "my ex's best friend (with blackbear)", "duration_ms": 138970, "explicit": true, "name": "my ex's best friend (with blackbear)", "popularity": 1, "acousticness": 0.00391, "danceability": 0.728, "energy": 0.685, "instrumentalness": 0, "key": 5, "liveness": 0.152, "loudness": -5.096, "mode": 0, "speechiness": 0.0433, "tempo": 124.934, "time_signature": 4, "valence": 0.33, "artist": "Machine Gun Kelly"}, {"album": "MAP OF THE SOUL : 7", "duration_ms": 246816, "explicit": false, "name": "ON (Feat. Sia)", "popularity": 7, "acousticness": 0.137, "danceability": 0.591, "energy": 0.848, "instrumentalness": 0, "key": 9, "liveness": 0.372, "loudness": -4.397, "mode": 0, "speechiness": 0.0828, "tempo": 105.922, "time_signature": 4, "valence": 0.386, "artist": "BTS"}, {"album": "MAMACITA", "duration_ms": 249142, "explicit": true, "name": "MAMACITA", "popularity": 69, "acousticness": 0.193, "danceability": 0.894, "energy": 0.635, "instrumentalness": 0.00105, "key": 2, "liveness": 0.0823, "loudness": -6.929, "mode": 1, "speechiness": 0.0473, "tempo": 105.013, "time_signature": 4, "valence": 0.428, "artist": "Black Eyed Peas"}, {"album": "Tusa", "duration_ms": 200960, "explicit": false, "name": "Tusa", "popularity": 78, "acousticness": 0.295, "danceability": 0.803, "energy": 0.715, "instrumentalness": 0.000134, "key": 2, "liveness": 0.0574, "loudness": -3.28, "mode": 1, "speechiness": 0.298, "tempo": 101.085, "time_signature": 4, "valence": 0.574, "artist": "KAROL G"}, {"album": "everything i wanted", "duration_ms": 245425, "explicit": false, "name": "everything i wanted", "popularity": 81, "acousticness": 0.902, "danceability": 0.704, "energy": 0.225, "instrumentalness": 0.657, "key": 6, "liveness": 0.106, "loudness": -14.454, "mode": 0, "speechiness": 0.0994, "tempo": 120.006, "time_signature": 4, "valence": 0.243, "artist": "Billie Eilish"}, {"album": "Be Kind (with Halsey)", "duration_ms": 172761, "explicit": false, "name": "Be Kind (with Halsey)", "popularity": 77, "acousticness": 0.00776, "danceability": 0.63, "energy": 0.633, "instrumentalness": 0, "key": 4, "liveness": 0.0541, "loudness": -7.088, "mode": 1, "speechiness": 0.0457, "tempo": 93.995, "time_signature": 4, "valence": 0.452, "artist": "Marshmello"}, {"album": "Divinely Uninspired To A Hellish Extent", "duration_ms": 182160, "explicit": false, "name": "Someone You Loved", "popularity": 84, "acousticness": 0.751, "danceability": 0.501, "energy": 0.405, "instrumentalness": 0, "key": 1, "liveness": 0.105, "loudness": -5.679, "mode": 1, "speechiness": 0.0319, "tempo": 109.891, "time_signature": 4, "valence": 0.446, "artist": "Lewis Capaldi"}, {"album": "Ride It", "duration_ms": 157605, "explicit": false, "name": "Ride It", "popularity": 81, "acousticness": 0.177, "danceability": 0.88, "energy": 0.751, "instrumentalness": 6.43e-05, "key": 7, "liveness": 0.106, "loudness": -4.258, "mode": 0, "speechiness": 0.0874, "tempo": 117.948, "time_signature": 4, "valence": 0.884, "artist": "Regard"}, {"album": "Lonely (with benny blanco)", "duration_ms": 149297, "explicit": true, "name": "Lonely (with benny blanco)", "popularity": 75, "acousticness": 0.864, "danceability": 0.631, "energy": 0.239, "instrumentalness": 0, "key": 11, "liveness": 0.116, "loudness": -7.071, "mode": 0, "speechiness": 0.0398, "tempo": 79.859, "time_signature": 4, "valence": 0.0927, "artist": "Justin Bieber"}, {"album": "UN DIA (ONE DAY) (Feat. Tainy)", "duration_ms": 232253, "explicit": false, "name": "UN DIA (ONE DAY) (Feat. Tainy)", "popularity": 75, "acousticness": 0.00536, "danceability": 0.571, "energy": 0.693, "instrumentalness": 0, "key": 6, "liveness": 0.173, "loudness": -8.234, "mode": 0, "speechiness": 0.0545, "tempo": 168.169, "time_signature": 4, "valence": 0.393, "artist": "J Balvin"}, {"album": "ily (i love you baby) (feat. Emilee)", "duration_ms": 176546, "explicit": false, "name": "ily (i love you baby) (feat. Emilee)", "popularity": 78, "acousticness": 0.0686, "danceability": 0.674, "energy": 0.774, "instrumentalness": 0.00188, "key": 11, "liveness": 0.393, "loudness": -7.567, "mode": 0, "speechiness": 0.0892, "tempo": 112.05, "time_signature": 4, "valence": 0.33, "artist": "Surf Mesa"}, {"album": "Future Nostalgia", "duration_ms": 193829, "explicit": false, "name": "Physical", "popularity": 75, "acousticness": 0.0137, "danceability": 0.647, "energy": 0.844, "instrumentalness": 0.000658, "key": 0, "liveness": 0.102, "loudness": -3.756, "mode": 1, "speechiness": 0.0457, "tempo": 146.967, "time_signature": 4, "valence": 0.746, "artist": "Dua Lipa"}, {"album": "PAPI JUANCHO", "duration_ms": 199112, "explicit": false, "name": "Haw\u00e1i", "popularity": 76, "acousticness": 0.185, "danceability": 0.783, "energy": 0.727, "instrumentalness": 2.46e-05, "key": 6, "liveness": 0.0626, "loudness": -3.454, "mode": 0, "speechiness": 0.389, "tempo": 180.067, "time_signature": 4, "valence": 0.558, "artist": "Maluma"}, {"album": "If the World Was Ending (feat. Julia Michaels)", "duration_ms": 208687, "explicit": false, "name": "If the World Was Ending (feat. Julia Michaels)", "popularity": 78, "acousticness": 0.866, "danceability": 0.464, "energy": 0.473, "instrumentalness": 0, "key": 1, "liveness": 0.109, "loudness": -10.086, "mode": 1, "speechiness": 0.129, "tempo": 75.801, "time_signature": 4, "valence": 0.604, "artist": "JP Saxe"}, {"album": "Translation", "duration_ms": 214934, "explicit": true, "name": "RITMO (Bad Boys For Life)", "popularity": 43, "acousticness": 0.0259, "danceability": 0.723, "energy": 0.704, "instrumentalness": 0.00109, "key": 10, "liveness": 0.792, "loudness": -7.088, "mode": 0, "speechiness": 0.0571, "tempo": 105.095, "time_signature": 4, "valence": 0.684, "artist": "Black Eyed Peas"}, {"album": "Sour Candy (with BLACKPINK)", "duration_ms": 157706, "explicit": false, "name": "Sour Candy (with BLACKPINK)", "popularity": 66, "acousticness": 0.0604, "danceability": 0.752, "energy": 0.87, "instrumentalness": 1.12e-05, "key": 9, "liveness": 0.489, "loudness": -3.812, "mode": 0, "speechiness": 0.0623, "tempo": 120.006, "time_signature": 4, "valence": 0.784, "artist": "Lady Gaga"}, {"album": "Legends Never Die", "duration_ms": 194621, "explicit": true, "name": "Wishing Well", "popularity": 2, "acousticness": 0.00336, "danceability": 0.65, "energy": 0.613, "instrumentalness": 0, "key": 9, "liveness": 0.267, "loudness": -6.13, "mode": 0, "speechiness": 0.128, "tempo": 149.972, "time_signature": 4, "valence": 0.0804, "artist": "Juice WRLD"}, {"album": "Cry Baby (Deluxe Edition)", "duration_ms": 179867, "explicit": true, "name": "Play Date", "popularity": 79, "acousticness": 0.612, "danceability": 0.68, "energy": 0.729, "instrumentalness": 0, "key": 5, "liveness": 0.224, "loudness": -5.077, "mode": 1, "speechiness": 0.0475, "tempo": 123.97, "time_signature": 4, "valence": 0.446, "artist": "Melanie Martinez"}, {"album": "Know Your Worth", "duration_ms": 181436, "explicit": false, "name": "Know Your Worth", "popularity": 71, "acousticness": 0.145, "danceability": 0.79, "energy": 0.694, "instrumentalness": 0.00252, "key": 9, "liveness": 0.281, "loudness": -7.726, "mode": 0, "speechiness": 0.0708, "tempo": 103.007, "time_signature": 4, "valence": 0.508, "artist": "Khalid"}, {"album": "Hollywood's Bleeding", "duration_ms": 157560, "explicit": false, "name": "Sunflower - Spider-Man: Into the Spider-Verse", "popularity": 79, "acousticness": 0.533, "danceability": 0.755, "energy": 0.522, "instrumentalness": 0, "key": 2, "liveness": 0.0685, "loudness": -4.368, "mode": 1, "speechiness": 0.0575, "tempo": 89.96, "time_signature": 4, "valence": 0.925, "artist": "Post Malone"}, {"album": "Ice Cream (with Selena Gomez)", "duration_ms": 175813, "explicit": false, "name": "Ice Cream (with Selena Gomez)", "popularity": 64, "acousticness": 0.0342, "danceability": 0.79, "energy": 0.729, "instrumentalness": 9.31e-05, "key": 9, "liveness": 0.0411, "loudness": -3.843, "mode": 1, "speechiness": 0.334, "tempo": 159.989, "time_signature": 4, "valence": 0.904, "artist": "BLACKPINK"}, {"album": "WHEN WE ALL FALL ASLEEP, WHERE DO WE GO?", "duration_ms": 194087, "explicit": false, "name": "bad guy", "popularity": 83, "acousticness": 0.328, "danceability": 0.701, "energy": 0.425, "instrumentalness": 0.13, "key": 7, "liveness": 0.1, "loudness": -10.965, "mode": 1, "speechiness": 0.375, "tempo": 135.128, "time_signature": 4, "valence": 0.562, "artist": "Billie Eilish"}, {"album": "Slime & B", "duration_ms": 176960, "explicit": true, "name": "Go Crazy", "popularity": 77, "acousticness": 0.316, "danceability": 0.755, "energy": 0.578, "instrumentalness": 0, "key": 0, "liveness": 0.25, "loudness": -8.932, "mode": 0, "speechiness": 0.145, "tempo": 94.148, "time_signature": 4, "valence": 0.581, "artist": "Chris Brown"}, {"album": "Wonder", "duration_ms": 172692, "explicit": false, "name": "Wonder", "popularity": 72, "acousticness": 0.131, "danceability": 0.333, "energy": 0.637, "instrumentalness": 1.8e-05, "key": 1, "liveness": 0.149, "loudness": -4.904, "mode": 0, "speechiness": 0.0581, "tempo": 139.898, "time_signature": 4, "valence": 0.132, "artist": "Shawn Mendes"}, {"album": "TKN (feat. Travis Scott)", "duration_ms": 129370, "explicit": false, "name": "TKN (feat. Travis Scott)", "popularity": 71, "acousticness": 0.192, "danceability": 0.776, "energy": 0.509, "instrumentalness": 1.49e-06, "key": 0, "liveness": 0.115, "loudness": -6.266, "mode": 0, "speechiness": 0.467, "tempo": 94.634, "time_signature": 4, "valence": 0.485, "artist": "ROSAL\u00cdA"}, {"album": "PARTYMOBILE", "duration_ms": 183219, "explicit": true, "name": "BELIEVE IT", "popularity": 70, "acousticness": 0.0902, "danceability": 0.43, "energy": 0.7, "instrumentalness": 0, "key": 6, "liveness": 0.216, "loudness": -5.35, "mode": 1, "speechiness": 0.264, "tempo": 158.373, "time_signature": 4, "valence": 0.731, "artist": "PARTYNEXTDOOR"}, {"album": "What A Man Gotta Do", "duration_ms": 180644, "explicit": false, "name": "What A Man Gotta Do", "popularity": 70, "acousticness": 0.00839, "danceability": 0.852, "energy": 0.698, "instrumentalness": 1.03e-06, "key": 9, "liveness": 0.0773, "loudness": -7.206, "mode": 1, "speechiness": 0.0629, "tempo": 113.039, "time_signature": 4, "valence": 0.324, "artist": "Jonas Brothers"}, {"album": "THE ALBUM", "duration_ms": 194765, "explicit": false, "name": "Lovesick Girls", "popularity": 72, "acousticness": 0.00559, "danceability": 0.654, "energy": 0.707, "instrumentalness": 0, "key": 6, "liveness": 0.0873, "loudness": -5.661, "mode": 1, "speechiness": 0.0664, "tempo": 127.97, "time_signature": 4, "valence": 0.448, "artist": "BLACKPINK"}, {"album": "Stupid Love", "duration_ms": 193530, "explicit": false, "name": "Stupid Love", "popularity": 31, "acousticness": 0.00146, "danceability": 0.676, "energy": 0.815, "instrumentalness": 0.00041, "key": 8, "liveness": 0.275, "loudness": -4.294, "mode": 1, "speechiness": 0.0625, "tempo": 117.973, "time_signature": 4, "valence": 0.796, "artist": "Lady Gaga"}, {"album": "Kid Krow", "duration_ms": 198040, "explicit": false, "name": "Heather", "popularity": 85, "acousticness": 0.584, "danceability": 0.357, "energy": 0.425, "instrumentalness": 0, "key": 5, "liveness": 0.322, "loudness": -7.301, "mode": 1, "speechiness": 0.0333, "tempo": 102.078, "time_signature": 3, "valence": 0.27, "artist": "Conan Gray"}, {"album": "YHLQMDLG", "duration_ms": 295176, "explicit": true, "name": "Safaera", "popularity": 79, "acousticness": 0.0103, "danceability": 0.607, "energy": 0.829, "instrumentalness": 0, "key": 2, "liveness": 0.107, "loudness": -4.074, "mode": 1, "speechiness": 0.379, "tempo": 96.172, "time_signature": 4, "valence": 0.685, "artist": "Bad Bunny"}, {"album": "HIGHEST IN THE ROOM", "duration_ms": 175720, "explicit": true, "name": "HIGHEST IN THE ROOM", "popularity": 81, "acousticness": 0.0546, "danceability": 0.598, "energy": 0.427, "instrumentalness": 5.83e-06, "key": 7, "liveness": 0.21, "loudness": -8.764, "mode": 0, "speechiness": 0.0317, "tempo": 76.469, "time_signature": 4, "valence": 0.0605, "artist": "Travis Scott"}, {"album": "Take You Dancing", "duration_ms": 190306, "explicit": false, "name": "Take You Dancing", "popularity": 79, "acousticness": 0.0332, "danceability": 0.789, "energy": 0.711, "instrumentalness": 0, "key": 2, "liveness": 0.0876, "loudness": -4.248, "mode": 1, "speechiness": 0.041, "tempo": 112.985, "time_signature": 4, "valence": 0.753, "artist": "Jason Derulo"}, {"album": "Circles", "duration_ms": 342040, "explicit": false, "name": "Good News", "popularity": 74, "acousticness": 0.853, "danceability": 0.794, "energy": 0.32, "instrumentalness": 0.134, "key": 1, "liveness": 0.112, "loudness": -12.92, "mode": 0, "speechiness": 0.173, "tempo": 174.088, "time_signature": 4, "valence": 0.241, "artist": "Mac Miller"}, {"album": "my future", "duration_ms": 208155, "explicit": false, "name": "my future", "popularity": 71, "acousticness": 0.795, "danceability": 0.444, "energy": 0.309, "instrumentalness": 0.132, "key": 8, "liveness": 0.352, "loudness": -10.956, "mode": 1, "speechiness": 0.062, "tempo": 104.745, "time_signature": 4, "valence": 0.0875, "artist": "Billie Eilish"}, {"album": "Shawn Mendes (Deluxe)", "duration_ms": 190799, "explicit": false, "name": "Se\u00f1orita", "popularity": 78, "acousticness": 0.0392, "danceability": 0.759, "energy": 0.548, "instrumentalness": 0, "key": 9, "liveness": 0.0828, "loudness": -6.049, "mode": 0, "speechiness": 0.029, "tempo": 116.967, "time_signature": 4, "valence": 0.749, "artist": "Shawn Mendes"}, {"album": "I\u2019m Ready (with Demi Lovato)", "duration_ms": 200838, "explicit": false, "name": "I\u2019m Ready (with Demi Lovato)", "popularity": 62, "acousticness": 0.00346, "danceability": 0.501, "energy": 0.674, "instrumentalness": 3.56e-05, "key": 5, "liveness": 0.282, "loudness": -6.363, "mode": 1, "speechiness": 0.0408, "tempo": 155.051, "time_signature": 4, "valence": 0.152, "artist": "Sam Smith"}, {"album": "HOLIDAY", "duration_ms": 154997, "explicit": true, "name": "HOLIDAY", "popularity": 74, "acousticness": 0.12, "danceability": 0.81, "energy": 0.511, "instrumentalness": 0, "key": 5, "liveness": 0.0832, "loudness": -6.924, "mode": 0, "speechiness": 0.164, "tempo": 151.947, "time_signature": 4, "valence": 0.837, "artist": "Lil Nas X"}, {"album": "Birds In The Trap Sing McKnight", "duration_ms": 243836, "explicit": true, "name": "goosebumps", "popularity": 83, "acousticness": 0.0847, "danceability": 0.841, "energy": 0.728, "instrumentalness": 0, "key": 7, "liveness": 0.149, "loudness": -3.37, "mode": 1, "speechiness": 0.0484, "tempo": 130.049, "time_signature": 4, "valence": 0.43, "artist": "Travis Scott"}, {"album": "Shoot For The Stars Aim For The Moon", "duration_ms": 213333, "explicit": true, "name": "Mood Swings (feat. Lil Tjay)", "popularity": 78, "acousticness": 0.487, "danceability": 0.48, "energy": 0.602, "instrumentalness": 0, "key": 10, "liveness": 0.0848, "loudness": -6.335, "mode": 0, "speechiness": 0.368, "tempo": 179.798, "time_signature": 4, "valence": 0.269, "artist": "Pop Smoke"}, {"album": "Positions", "duration_ms": 167989, "explicit": true, "name": "motive (with Doja Cat)", "popularity": 78, "acousticness": 0.0681, "danceability": 0.789, "energy": 0.742, "instrumentalness": 0, "key": 10, "liveness": 0.166, "loudness": -5.664, "mode": 0, "speechiness": 0.0652, "tempo": 116.965, "time_signature": 4, "valence": 0.661, "artist": "Ariana Grande"}]